pytest_toolkit
tests
