Metadata-Version: 2.1
Name: pytest_toolkit
Version: 0.1.3
Summary: Useful utils for testing
Home-page: https://github.com/lev4ek0/pytest_toolkit
Author: Lev Belous
Author-email: leva22.08.01@inbox.ru
Requires-Python: >=3.10
Requires-Dist: deepdiff
